ndc_parser/__init__.py
ndc_parser/ndc_parser.py
ndc_parser-0.1.dist-info/LICENSE.txt
ndc_parser-0.1.dist-info/METADATA
ndc_parser-0.1.dist-info/WHEEL
ndc_parser-0.1.dist-info/top_level.txt
ndc_parser-0.1.dist-info/RECORD
