Metadata-Version: 2.1
Name: ndc-parser
Version: 0.1
Summary: NDC Parser
Home-page: https://github.com/ndc-dev/python-parser
Author: CALIL Inc.
Author-email: info@calil.jp
License: MIT
Keywords: NDC Nippon Decimal Classification Parser
Platform: UNKNOWN
